ovos_skill_fallback_unknown/LICENSE
ovos_skill_fallback_unknown/MANIFEST.in
ovos_skill_fallback_unknown/README.md
ovos_skill_fallback_unknown/__init__.py
ovos_skill_fallback_unknown/requirements.txt
ovos_skill_fallback_unknown/version.py
ovos_skill_fallback_unknown/locale/ca-es/question.dialog
ovos_skill_fallback_unknown/locale/ca-es/question.voc
ovos_skill_fallback_unknown/locale/ca-es/unknown.dialog
ovos_skill_fallback_unknown/locale/ca-es/who.is.dialog
ovos_skill_fallback_unknown/locale/ca-es/who.is.voc
ovos_skill_fallback_unknown/locale/ca-es/why.is.dialog
ovos_skill_fallback_unknown/locale/ca-es/why.is.voc
ovos_skill_fallback_unknown/locale/cs-cz/question.dialog
ovos_skill_fallback_unknown/locale/cs-cz/question.voc
ovos_skill_fallback_unknown/locale/cs-cz/unknown.dialog
ovos_skill_fallback_unknown/locale/cs-cz/who.is.dialog
ovos_skill_fallback_unknown/locale/cs-cz/who.is.voc
ovos_skill_fallback_unknown/locale/cs-cz/why.is.dialog
ovos_skill_fallback_unknown/locale/cs-cz/why.is.voc
ovos_skill_fallback_unknown/locale/da-dk/question.dialog
ovos_skill_fallback_unknown/locale/da-dk/question.voc
ovos_skill_fallback_unknown/locale/da-dk/unknown.dialog
ovos_skill_fallback_unknown/locale/da-dk/who.is.dialog
ovos_skill_fallback_unknown/locale/da-dk/who.is.voc
ovos_skill_fallback_unknown/locale/da-dk/why.is.dialog
ovos_skill_fallback_unknown/locale/da-dk/why.is.voc
ovos_skill_fallback_unknown/locale/de-de/question.dialog
ovos_skill_fallback_unknown/locale/de-de/question.voc
ovos_skill_fallback_unknown/locale/de-de/unknown.dialog
ovos_skill_fallback_unknown/locale/de-de/who.is.dialog
ovos_skill_fallback_unknown/locale/de-de/who.is.voc
ovos_skill_fallback_unknown/locale/de-de/why.is.dialog
ovos_skill_fallback_unknown/locale/de-de/why.is.voc
ovos_skill_fallback_unknown/locale/en-us/question.dialog
ovos_skill_fallback_unknown/locale/en-us/question.voc
ovos_skill_fallback_unknown/locale/en-us/unknown.dialog
ovos_skill_fallback_unknown/locale/en-us/who.is.dialog
ovos_skill_fallback_unknown/ovos_skill_fallback_unknown.egg-info/PKG-INFO
ovos_skill_fallback_unknown/ovos_skill_fallback_unknown.egg-info/SOURCES.txt
ovos_skill_fallback_unknown/ovos_skill_fallback_unknown.egg-info/dependency_links.txt
ovos_skill_fallback_unknown/ovos_skill_fallback_unknown.egg-info/entry_points.txt
ovos_skill_fallback_unknown/ovos_skill_fallback_unknown.egg-info/requires.txt
ovos_skill_fallback_unknown/ovos_skill_fallback_unknown.egg-info/top_level.txt
ovos_skill_fallback_unknown-0.1.9.dist-info/LICENSE
ovos_skill_fallback_unknown-0.1.9.dist-info/METADATA
ovos_skill_fallback_unknown-0.1.9.dist-info/WHEEL
ovos_skill_fallback_unknown-0.1.9.dist-info/entry_points.txt
ovos_skill_fallback_unknown-0.1.9.dist-info/top_level.txt
ovos_skill_fallback_unknown-0.1.9.dist-info/RECORD
