Metadata-Version: 2.1
Name: ovos-skill-fallback-unknown
Version: 0.1.9
Home-page: https://github.com/OpenVoiceOS/ovos-skill-fallback-unknown
Author: OpenVoiceOS
Author-email: jarbasai@mailfence.com
License: Apache-2.0
Keywords: ovos skill plugin
License-File: LICENSE
Requires-Dist: ovos-workshop<8.0.0,>=6.0.0
